mangdl/__init__.py
mangdl/__main__.py
mangdl/cli.py
mangdl/providers.py
mangdl/API/Base.py
mangdl/API/__init__.py
mangdl/API/Providers/__init__.py
mangdl/API/Providers/flamescans copy.py
mangdl/API/Providers/flamescans.py
mangdl/API/Providers/mangadex.py
mangdl/API/Providers/manganato.py
mangdl/API/Providers/sample.py
mangdl/api/__init__.py
mangdl/api/base.py
mangdl/api/providers/__init__.py
mangdl/api/providers/acescans.py
mangdl/api/providers/chibimanga.py
mangdl/api/providers/danke.py
mangdl/api/providers/firstkiss.py
mangdl/api/providers/flamescans.py
mangdl/api/providers/hachirumi.py
mangdl/api/providers/mangadex.py
mangdl/api/providers/mangakomi.py
mangdl/api/providers/manganato.py
mangdl/api/providers/mangasushi.py
mangdl/api/providers/mangazuki.py
mangdl/api/providers/paeanscans.py
mangdl/api/providers/sample.py
mangdl/api/providers/setsuscans.py
mangdl/api/providers/vinmanga.py
mangdl/api/providers/xunscans.py
mangdl/api/providers/zinmanga.py
mangdl/api/providers/templates/__init__.py
mangdl/api/providers/templates/fs_wp.py
mangdl/api/providers/templates/generic.py
mangdl/api/providers/templates/guya.py
mangdl/api/providers/templates/wordpress.py
mangdl/utils/__init__.py
mangdl/utils/colours.yaml
mangdl/utils/config.json
mangdl/utils/config.yaml
mangdl/utils/exceptions.py
mangdl/utils/globals.py
mangdl/utils/log.py
mangdl/utils/settings.py
mangdl/utils/stg.json
mangdl/utils/style.py
mangdl/utils/utils.py
MangDL-2.0.0.dist-info/METADATA
MangDL-2.0.0.dist-info/WHEEL
MangDL-2.0.0.dist-info/entry_points.txt
MangDL-2.0.0.dist-info/top_level.txt
MangDL-2.0.0.dist-info/RECORD
