Metadata-Version: 2.1
Name: MangDL
Version: 2.0.0
Summary: The most inefficent Manga downloader for PC
Home-page: https://github.com/MangDL/MangDL
Author: whinee
Author-email: whinyaan@gmail.com
License: MIT
Project-URL: Documentation, http://mangdl.rf.gd/docs
Project-URL: Source, https://github.com/MangDL/MangDL/
Project-URL: Tracker, https://github.com/MangDL/MangDL/issues
Keywords: development python windows macos linux cli wordpress metadata scraper downloader zip tar rar manga provider reader cbr cbz cbt 7zip cb7
Platform: UNKNOWN
Classifier: Programming Language :: Python :: 3
Classifier: License :: OSI Approved :: MIT License
Classifier: Operating System :: OS Independent
Requires-Python: >=3.9
Requires-Dist: arrow
Requires-Dist: BeautifulSoup4
Requires-Dist: click
Requires-Dist: httpx
Requires-Dist: lxml
Requires-Dist: patool
Requires-Dist: pyyaml
Requires-Dist: tabulate
Requires-Dist: toml
Requires-Dist: tqdm
Requires-Dist: yachalk
Requires-Dist: yarl
